.hgignore
CHANGES.txt
LICENSE.txt
MANIFEST.in
README.txt
bootstrap.py
buildout.cfg
setup.py
js/__init__.py
js.smoke.egg-info/PKG-INFO
js.smoke.egg-info/SOURCES.txt
js.smoke.egg-info/dependency_links.txt
js.smoke.egg-info/entry_points.txt
js.smoke.egg-info/namespace_packages.txt
js.smoke.egg-info/not-zip-safe
js.smoke.egg-info/requires.txt
js.smoke.egg-info/top_level.txt
js/smoke/__init__.py
js/smoke/test_smoke.txt
js/smoke/resources/smoke.css
js/smoke/resources/smoke.js
js/smoke/resources/smoke.min.js
js/smoke/resources/themes/100s.css
js/smoke/resources/themes/dark.css
js/smoke/resources/themes/tiger.css