Metadata-Version: 1.0
Name: js.smoke
Version: 0.1
Summary: fanstatic smoke.js.
Home-page: UNKNOWN
Author: Fanstatic Developers
Author-email: fanstatic@googlegroups.com
License: BSD
Platform: UNKNOWN
